<?xml version="1.0" encoding="UTF-8" standalone="yes"?>
<unit   revision="0.9.5" language="C++" filename="12305400.cpp"><comment type="line">//Language: GNU C++</comment>


<include>#<directive>include</directive> <file>&lt;bits/stdc++.h&gt;</file></include>
 
<using>using <namespace>namespace <name>std</name>;</namespace></using>
 
<define>#<directive>define</directive> <macro><name>fr</name><parameter_list>(<parameter><type><name>a</name></type></parameter>,<parameter><type><name>b</name></type></parameter>,<parameter><type><name>c</name></type></parameter>)</parameter_list></macro> <value>for(int (a) = (b); (a) &lt; (c); ++(a))</value></define>
<define>#<directive>define</directive> <macro><name>rp</name><parameter_list>(<parameter><type><name>a</name></type></parameter>,<parameter><type><name>b</name></type></parameter>)</parameter_list></macro> <value>fr(a,0,b)</value></define>
<define>#<directive>define</directive> <macro><name>fre</name><parameter_list>(<parameter><type><name>a</name></type></parameter>,<parameter><type><name>b</name></type></parameter>)</parameter_list></macro> <value>for(int a = adj[b]; ~a; a = ant[a])</value></define>
<define>#<directive>define</directive> <macro><name>cl</name><parameter_list>(<parameter><type><name>a</name></type></parameter>,<parameter><type><name>b</name></type></parameter>)</parameter_list></macro> <value>memset((a), (b), sizeof(a))</value></define>
<define>#<directive>define</directive> <macro><name>sc</name><parameter_list>(<parameter><type><name>a</name></type></parameter>)</parameter_list></macro> <value>scanf("%d", &amp;a)</value></define>
<define>#<directive>define</directive> <macro><name>sc2</name><parameter_list>(<parameter><type><name>a</name></type></parameter>,<parameter><type><name>b</name></type></parameter>)</parameter_list></macro> <value>scanf("%d%d", &amp;a, &amp;b)</value></define>
<define>#<directive>define</directive> <macro><name>sc3</name><parameter_list>(<parameter><type><name>a</name></type></parameter>,<parameter><type><name>b</name></type></parameter>,<parameter><type><name>c</name></type></parameter>)</parameter_list></macro> <value>scanf("%d%d%d", &amp;a, &amp;b, &amp;c)</value></define>
<define>#<directive>define</directive> <macro><name>scs</name><parameter_list>(<parameter><type><name>s</name></type></parameter>)</parameter_list></macro> <value>scanf("%s", s)</value></define>
<define>#<directive>define</directive> <macro><name>pri</name><parameter_list>(<parameter><type><name>x</name></type></parameter>)</parameter_list></macro> <value>printf("%d\n", x)</value></define>
 
<define>#<directive>define</directive> <macro><name>iter</name><parameter_list>(<parameter><type><name>a</name></type></parameter>)</parameter_list></macro> <value>__typeof((a).begin())</value></define>
<define>#<directive>define</directive> <macro><name>fore</name><parameter_list>(<parameter><type><name>a</name></type></parameter>,<parameter><type><name>b</name></type></parameter>)</parameter_list></macro> <value>for(iter(b) a = (b).begin(); a != (b).end(); ++a)</value></define>
 
<define>#<directive>define</directive> <macro><name>st</name></macro> <value>first</value></define>
<define>#<directive>define</directive> <macro><name>nd</name></macro> <value>second</value></define>
<define>#<directive>define</directive> <macro><name>mp</name></macro> <value>make_pair</value></define>
<define>#<directive>define</directive> <macro><name>pb</name></macro> <value>push_back</value></define>
 
<define>#<directive>define</directive> <macro><name>db</name><parameter_list>(<parameter><type><name>x</name></type></parameter>)</parameter_list></macro> <value>cerr &lt;&lt; #x &lt;&lt; " == " &lt;&lt; x &lt;&lt; endl</value></define>
<define>#<directive>define</directive> <macro><name>dbs</name><parameter_list>(<parameter><type><name>x</name></type></parameter>)</parameter_list></macro> <value>cerr &lt;&lt; x &lt;&lt; endl</value></define>
<define>#<directive>define</directive> <macro><name>_</name></macro> <value>&lt;&lt; ", " &lt;&lt;</value></define>
 
<decl_stmt><decl><type><specifier>const</specifier> <name>int</name></type> <name>oo</name> <init>= <expr><literal type="number">0x3f3f3f3f</literal></expr></init></decl>;</decl_stmt>
 
<typedef>typedef <type><name>long</name> <name>long</name></type> <name>ll</name>;</typedef>
<typedef>typedef <type><name><name>pair</name><argument_list type="generic">&lt;<argument><expr><name>int</name></expr></argument>,<argument><expr><name>int</name></expr></argument>&gt;</argument_list></name></type> <name>pii</name>;</typedef>
<typedef>typedef <type><name><name>vector</name><argument_list type="generic">&lt;<argument><expr><name>int</name></expr></argument>&gt;</argument_list></name></type> <name>vi</name>;</typedef>
<typedef>typedef <type><name><name>vector</name><argument_list type="generic">&lt; <argument><expr><name>vi</name></expr></argument> &gt;</argument_list></name></type> <name>vii</name>;</typedef>

<decl_stmt><decl><type><name>int</name></type> <name><name>cnt</name><index>[<expr><literal type="number">1000100</literal></expr>]</index></name></decl>;</decl_stmt>
<decl_stmt><decl><type><name>int</name></type> <name><name>l</name><index>[<expr><literal type="number">1000100</literal></expr>]</index></name></decl>, <decl><type ref="prev"/><name><name>r</name><index>[<expr><literal type="number">1000100</literal></expr>]</index></name></decl>;</decl_stmt>
<function><type><name>int</name></type> <name>main</name><parameter_list>()</parameter_list> <block>{
	<decl_stmt><decl><type><name>int</name></type> <name>n</name></decl>;</decl_stmt>
	<expr_stmt><expr><call><name>sc</name><argument_list>(<argument><expr><name>n</name></expr></argument>)</argument_list></call></expr>;</expr_stmt>
	<expr_stmt><expr><call><name>cl</name><argument_list>(<argument><expr><name>cnt</name></expr></argument>,<argument><expr><literal type="number">0</literal></expr></argument>)</argument_list></call></expr>;</expr_stmt>
	<expr_stmt><expr><call><name>cl</name><argument_list>(<argument><expr><name>l</name></expr></argument>,<argument><expr><operator>-</operator><literal type="number">1</literal></expr></argument>)</argument_list></call></expr>;</expr_stmt>
	<decl_stmt><decl><type><name>int</name></type> <name>m</name> <init>= <expr><literal type="number">0</literal></expr></init></decl>;</decl_stmt>
	<macro><name>rp</name><argument_list>(<argument>i</argument>,<argument>n</argument>)</argument_list></macro> <block>{
		<decl_stmt><decl><type><name>int</name></type> <name>a</name></decl>;</decl_stmt>
		<expr_stmt><expr><call><name>sc</name><argument_list>(<argument><expr><name>a</name></expr></argument>)</argument_list></call></expr>;</expr_stmt>
		<if>if <condition>(<expr><name><name>l</name><index>[<expr><name>a</name></expr>]</index></name> <operator>==</operator> <operator>-</operator><literal type="number">1</literal></expr>)</condition><then> <block type="pseudo"><expr_stmt><expr><name><name>l</name><index>[<expr><name>a</name></expr>]</index></name> <operator>=</operator> <name>i</name></expr>;</expr_stmt></block></then></if>
		<expr_stmt><expr><name><name>r</name><index>[<expr><name>a</name></expr>]</index></name> <operator>=</operator> <name>i</name></expr>;</expr_stmt>
		<expr_stmt><expr><name><name>cnt</name><index>[<expr><name>a</name></expr>]</index></name><operator>++</operator></expr>;</expr_stmt>
		<expr_stmt><expr><name>m</name> <operator>=</operator> <call><name>max</name><argument_list>(<argument><expr><name>m</name></expr></argument>, <argument><expr><name><name>cnt</name><index>[<expr><name>a</name></expr>]</index></name></expr></argument>)</argument_list></call></expr>;</expr_stmt>
	}</block>
	<decl_stmt><decl><type><name>int</name></type> <name>best</name> <init>= <expr><literal type="number">100000000</literal></expr></init></decl>;</decl_stmt>
	<decl_stmt><decl><type><name>int</name></type> <name>id</name> <init>= <expr><literal type="number">0</literal></expr></init></decl>;</decl_stmt>
	<macro><name>fr</name><argument_list>(<argument>i</argument>,<argument><literal type="number">1</literal></argument>,<argument><literal type="number">1000001</literal></argument>)</argument_list></macro> <block>{
		<if>if <condition>(<expr><name><name>cnt</name><index>[<expr><name>i</name></expr>]</index></name> <operator>==</operator> <name>m</name></expr>)</condition><then> <block>{
			<if>if <condition>(<expr><name><name>r</name><index>[<expr><name>i</name></expr>]</index></name><operator>-</operator><name><name>l</name><index>[<expr><name>i</name></expr>]</index></name> <operator>&lt;</operator> <name>best</name></expr>)</condition><then> <block>{
				<expr_stmt><expr><name>best</name> <operator>=</operator> <name><name>r</name><index>[<expr><name>i</name></expr>]</index></name> <operator>-</operator> <name><name>l</name><index>[<expr><name>i</name></expr>]</index></name></expr>;</expr_stmt>
				<expr_stmt><expr><name>id</name> <operator>=</operator> <name>i</name></expr>;</expr_stmt>
			}</block></then></if>
		}</block></then></if>
	}</block>
	<expr_stmt><expr><call><name>printf</name><argument_list>(<argument><expr><literal type="string">"%d %d\n"</literal></expr></argument>, <argument><expr><name><name>l</name><index>[<expr><name>id</name></expr>]</index></name><operator>+</operator><literal type="number">1</literal></expr></argument>, <argument><expr><name><name>r</name><index>[<expr><name>id</name></expr>]</index></name><operator>+</operator><literal type="number">1</literal></expr></argument>)</argument_list></call></expr>;</expr_stmt>
}</block></function></unit>
