<?xml version="1.0" encoding="UTF-8" standalone="yes"?>
<unit xmlns="http://www.srcML.org/srcML/src" xmlns:cpp="http://www.srcML.org/srcML/cpp" revision="0.9.5" language="C++" filename="cpp/12375100.cpp"><comment type="line">//Language: GNU C++11</comment>


<comment type="line">//by dezhonger</comment>
<cpp:include>#<cpp:directive>include</cpp:directive> <cpp:file>&lt;iostream&gt;</cpp:file></cpp:include>
<cpp:include>#<cpp:directive>include</cpp:directive> <cpp:file>&lt;cmath&gt;</cpp:file></cpp:include>
<cpp:include>#<cpp:directive>include</cpp:directive> <cpp:file>&lt;algorithm&gt;</cpp:file></cpp:include>
<cpp:include>#<cpp:directive>include</cpp:directive> <cpp:file>&lt;string&gt;</cpp:file></cpp:include>
<cpp:include>#<cpp:directive>include</cpp:directive> <cpp:file>&lt;deque&gt;</cpp:file></cpp:include>
<cpp:include>#<cpp:directive>include</cpp:directive> <cpp:file>&lt;cstring&gt;</cpp:file></cpp:include>
<cpp:include>#<cpp:directive>include</cpp:directive> <cpp:file>&lt;cstdio&gt;</cpp:file></cpp:include>
<cpp:include>#<cpp:directive>include</cpp:directive> <cpp:file>&lt;vector&gt;</cpp:file></cpp:include>
<cpp:include>#<cpp:directive>include</cpp:directive> <cpp:file>&lt;set&gt;</cpp:file></cpp:include>
<cpp:include>#<cpp:directive>include</cpp:directive> <cpp:file>&lt;map&gt;</cpp:file></cpp:include>
<cpp:include>#<cpp:directive>include</cpp:directive> <cpp:file>&lt;queue&gt;</cpp:file></cpp:include>
<cpp:include>#<cpp:directive>include</cpp:directive> <cpp:file>&lt;cstdlib&gt;</cpp:file></cpp:include>
<cpp:include>#<cpp:directive>include</cpp:directive> <cpp:file>&lt;iomanip&gt;</cpp:file></cpp:include>
<cpp:include>#<cpp:directive>include</cpp:directive> <cpp:file>&lt;stack&gt;</cpp:file></cpp:include>
<using>using <namespace>namespace <name>std</name>;</namespace></using>

<cpp:define>#<cpp:directive>define</cpp:directive> <cpp:macro><name>rep</name><parameter_list>(<parameter><type><name>i</name></type></parameter>, <parameter><type><name>a</name></type></parameter>, <parameter><type><name>b</name></type></parameter>)</parameter_list></cpp:macro> <cpp:value>for( i = (a); i &lt;= (b); i++)</cpp:value></cpp:define>
<cpp:define>#<cpp:directive>define</cpp:directive> <cpp:macro><name>reps</name><parameter_list>(<parameter><type><name>i</name></type></parameter>, <parameter><type><name>a</name></type></parameter>, <parameter><type><name>b</name></type></parameter>)</parameter_list></cpp:macro> <cpp:value>for( i = (a); i &lt; (b); i++)</cpp:value></cpp:define>
<cpp:define>#<cpp:directive>define</cpp:directive> <cpp:macro><name>pb</name></cpp:macro> <cpp:value>push_back</cpp:value></cpp:define>
<cpp:define>#<cpp:directive>define</cpp:directive> <cpp:macro><name>ps</name></cpp:macro> <cpp:value>push</cpp:value></cpp:define>
<cpp:define>#<cpp:directive>define</cpp:directive> <cpp:macro><name>mp</name></cpp:macro> <cpp:value>make_pair</cpp:value></cpp:define>
<cpp:define>#<cpp:directive>define</cpp:directive> <cpp:macro><name>CLR</name><parameter_list>(<parameter><type><name>x</name></type></parameter>,<parameter><type><name>t</name></type></parameter>)</parameter_list></cpp:macro> <cpp:value>memset(x,t,sizeof x)</cpp:value></cpp:define>
<cpp:define>#<cpp:directive>define</cpp:directive> <cpp:macro><name>LEN</name><parameter_list>(<parameter><type><name>X</name></type></parameter>)</parameter_list></cpp:macro> <cpp:value>strlen(X)</cpp:value></cpp:define>
<cpp:define>#<cpp:directive>define</cpp:directive> <cpp:macro><name>F</name></cpp:macro> <cpp:value>first</cpp:value></cpp:define>
<cpp:define>#<cpp:directive>define</cpp:directive> <cpp:macro><name>S</name></cpp:macro> <cpp:value>second</cpp:value></cpp:define>
<cpp:define>#<cpp:directive>define</cpp:directive> <cpp:macro><name>Debug</name><parameter_list>(<parameter><type><name>x</name></type></parameter>)</parameter_list></cpp:macro> <cpp:value>cout&lt;&lt;#x&lt;&lt;"="&lt;&lt;x&lt;&lt;endl;</cpp:value></cpp:define>


<decl_stmt><decl><type><specifier>const</specifier> <name>double</name></type> <name>euler_r</name> <init>= <expr><literal type="number">0.57721566490153286060651209</literal></expr></init></decl>;</decl_stmt>
<decl_stmt><decl><type><specifier>const</specifier> <name>double</name></type> <name>pi</name> <init>= <expr><literal type="number">3.141592653589793238462643383279</literal></expr></init></decl>;</decl_stmt>
<decl_stmt><decl><type><specifier>const</specifier> <name>double</name></type> <name>E</name> <init>= <expr><literal type="number">2.7182818284590452353602874713526</literal></expr></init></decl>;</decl_stmt>
<decl_stmt><decl><type><specifier>const</specifier> <name>int</name></type> <name>inf</name><init>=<expr><operator>~</operator><literal type="number">0U</literal><operator>&gt;&gt;</operator><literal type="number">1</literal></expr></init></decl>;</decl_stmt>
<decl_stmt><decl><type><specifier>const</specifier> <name>int</name></type> <name>MOD</name> <init>= <expr><call><name>int</name><argument_list>(<argument><expr><literal type="number">1e9</literal></expr></argument>)</argument_list></call> <operator>+</operator> <literal type="number">7</literal></expr></init></decl>;</decl_stmt>
<decl_stmt><decl><type><specifier>const</specifier> <name>double</name></type> <name>EPS</name><init>=<expr><literal type="number">1e-6</literal></expr></init></decl>;</decl_stmt>
<decl_stmt><decl><type><specifier>const</specifier> <name>int</name></type> <name>mod</name> <init>= <expr><call><name>int</name><argument_list>(<argument><expr><literal type="number">1e9</literal></expr></argument>)</argument_list></call> <operator>+</operator> <literal type="number">7</literal></expr></init></decl>;</decl_stmt>
<typedef>typedef <type><name>long</name> <name>long</name></type> <name>ll</name>;</typedef>
<typedef>typedef <type><name>long</name> <name>long</name></type> <name>LL</name>;</typedef>
<function><type><name>ll</name></type> <name>powmod</name><parameter_list>(<parameter><decl><type><name>ll</name></type> <name>a</name></decl></parameter>,<parameter><decl><type><name>ll</name></type> <name>b</name></decl></parameter>)</parameter_list> <block>{<decl_stmt><decl><type><name>ll</name></type> <name>res</name><init>=<expr><literal type="number">1</literal></expr></init></decl>;</decl_stmt><expr_stmt><expr><name>a</name><operator>%=</operator><name>mod</name></expr>;</expr_stmt><for>for<control>(<init>;</init><condition><expr><name>b</name></expr>;</condition><incr><expr><name>b</name><operator>&gt;&gt;=</operator><literal type="number">1</literal></expr></incr>)</control><block>{<if>if<condition>(<expr><name>b</name><operator>&amp;</operator><literal type="number">1</literal></expr>)</condition><then><block type="pseudo"><expr_stmt><expr><name>res</name><operator>=</operator><name>res</name><operator>*</operator><name>a</name><operator>%</operator><name>mod</name></expr>;</expr_stmt></block></then></if><expr_stmt><expr><name>a</name><operator>=</operator><name>a</name><operator>*</operator><name>a</name><operator>%</operator><name>mod</name></expr>;</expr_stmt>}</block></for><return>return <expr><name>res</name></expr>;</return>}</block></function>


<comment type="line">//dp[i] qianmian you duoshao ge i/k.</comment>
<decl_stmt><decl><type><name>int</name></type> <name><name>a</name><index>[<expr><literal type="number">200010</literal></expr>]</index></name></decl>;</decl_stmt>
<decl_stmt><decl><type><name><name>map</name><argument_list type="generic">&lt;<argument><expr><name>LL</name></expr></argument>, <argument><expr><name>int</name></expr></argument>&gt;</argument_list></name></type> <name>ma</name></decl>, <decl><type ref="prev"/><name>mb</name></decl>;</decl_stmt><function><type><name>int</name></type> <name>main</name><parameter_list>()</parameter_list>
<block>{
    <comment type="line">//freopen("in.txt","r",stdin);</comment>
    <comment type="line">//freopen("out.txt","w",stdout);</comment>
    <comment type="line">//ios_base::sync_with_stdio(0);</comment>
    <decl_stmt><decl><type><name>LL</name></type> <name>n</name></decl>, <decl><type ref="prev"/><name>k</name></decl>;</decl_stmt>
    <expr_stmt><expr><name>cin</name> <operator>&gt;&gt;</operator><name>n</name> <operator>&gt;&gt;</operator> <name>k</name></expr>;</expr_stmt>
    <decl_stmt><decl><type><name>LL</name></type> <name>x</name></decl>;</decl_stmt>
    <decl_stmt><decl><type><name>LL</name></type> <name>ans</name> <init>= <expr><literal type="number">0</literal></expr></init></decl>;</decl_stmt>
    <for>for<control>(<init><decl><type><name>int</name></type> <name>i</name> <init>= <expr><literal type="number">1</literal></expr></init></decl>;</init> <condition><expr><name>i</name> <operator>&lt;=</operator> <name>n</name></expr> ;</condition><incr><expr><name>i</name><operator>++</operator></expr></incr>)</control>
    <block>{
        <expr_stmt><expr><name>cin</name> <operator>&gt;&gt;</operator> <name>x</name></expr>;</expr_stmt>
        <expr_stmt><expr><name><name>a</name><index>[<expr><name>i</name></expr>]</index></name> <operator>=</operator> <name>x</name></expr>;</expr_stmt>
        <expr_stmt><expr><name><name>ma</name><index>[<expr><name>x</name></expr>]</index></name><operator>++</operator></expr>;</expr_stmt>
    }</block></for>

    <expr_stmt><expr><name><name>ma</name><index>[<expr><name><name>a</name><index>[<expr><literal type="number">1</literal></expr>]</index></name></expr>]</index></name><operator>--</operator></expr>;</expr_stmt>
    <expr_stmt><expr><name><name>mb</name><index>[<expr><name><name>a</name><index>[<expr><literal type="number">1</literal></expr>]</index></name></expr>]</index></name><operator>++</operator></expr>;</expr_stmt>
    <for>for<control>(<init><decl><type><name>int</name></type> <name>i</name> <init>= <expr><literal type="number">2</literal></expr></init></decl>;</init> <condition><expr><name>i</name> <operator>&lt;</operator> <name>n</name></expr>;</condition> <incr><expr><name>i</name><operator>++</operator></expr></incr>)</control>
    <block>{
        <expr_stmt><expr><name>x</name> <operator>=</operator> <name><name>a</name><index>[<expr><name>i</name></expr>]</index></name></expr>;</expr_stmt>
        <expr_stmt><expr><name><name>ma</name><index>[<expr><name>x</name></expr>]</index></name><operator>--</operator></expr>;</expr_stmt>
        <if>if<condition>(<expr><name>x</name> <operator>%</operator> <name>k</name> <operator>==</operator> <literal type="number">0</literal></expr>)</condition><then>
        <block>{
            <decl_stmt><decl><type><name>LL</name></type> <name>l</name> <init>=<expr><name><name>mb</name><index>[<expr><name>x</name><operator>/</operator><name>k</name></expr>]</index></name></expr></init></decl>;</decl_stmt>
            <decl_stmt><decl><type><name>LL</name></type> <name>r</name> <init>= <expr><name><name>ma</name><index>[<expr><name>x</name><operator>*</operator><name>k</name></expr>]</index></name></expr></init></decl>;</decl_stmt>
            <expr_stmt><expr><name>ans</name> <operator>=</operator> <name>ans</name> <operator>+</operator> <literal type="number">1LL</literal> <operator>*</operator> <name>l</name> <operator>*</operator> <name>r</name></expr>;</expr_stmt>
        }</block></then></if>
        <expr_stmt><expr><name><name>mb</name><index>[<expr><name>x</name></expr>]</index></name><operator>++</operator></expr>;</expr_stmt>

    }</block></for>


    <expr_stmt><expr><name>cout</name> <operator>&lt;&lt;</operator><name>ans</name> <operator>&lt;&lt;</operator> <name>endl</name></expr>;</expr_stmt>
    <return>return <expr><literal type="number">0</literal></expr>;</return>
}</block></function>
</unit>
